{
  "4.4A": {
    "Main DPS": {
      "SS": [
        "Neuvillette-Best-Builds",
        "383712",
        "314347",
        "337161",
        "417194",
        "345540"
      ],
      "S": [
        "315215",
        "Gaming-Best-Builds",
        "345514",
        "305862",
        "Wriothesley-Best-Builds",
        "382082",
        "297518",
        "Nahida-Best-Builds",
        "312173"
      ],
      "A": [
        "297527",
        "309656",
        "345461",
        "333497",
        "315233",
        "Keqing-Best-Builds",
        "297523",
        "328764"
      ],
      "B": [
        "328765",
        "345516",
        "297521",
        "Kaveh-Best-Builds",
        "297529",
        "337140",
        "383715",
        "417207"
      ],
      "C": ["297519", "297524", "297516"],
      "D": [
        "Dehya-Best-Builds",
        "314177",
        "305873",
        "297528",
        "297532",
        "337957"
      ]
    },
    "Sub-DPS": {
      "SS": [
        "Nahida-Best-Builds",
        "Furina-Best-Builds",
        "297531",
        "372781",
        "297530",
        "337161",
        "332826"
      ],
      "S": ["297524", "327533", "383715", "346199", "417194", "312182"],
      "A": [
        "Venti-Best-Builds",
        "312173",
        "Mona-Best-Builds",
        "297528",
        "314177",
        "382079",
        "345514",
        "297525",
        "412428"
      ],
      "B": [
        "337140",
        "337141",
        "409556",
        "426201",
        "381807",
        "345879",
        "386486",
        "305858",
        "297516",
        "Dehya-Best-Builds",
        "297536",
        "Lisa-Best-Builds"
      ],
      "C": ["297532", "305873", "333496", "386384"],
      "D": ["297538", "297535", "297537", "416602"]
    },
    "Support": {
      "SS": [
        "Bennett-Best-Builds",
        "Furina-Best-Builds",
        "332826",
        "Nahida-Best-Builds",
        "305858",
        "314348",
        "337140"
      ],
      "S": [
        "337161",
        "Mona-Best-Builds",
        "Xianyun-Best-Builds",
        "346620",
        "297536",
        "426201",
        "297525",
        "391897"
      ],
      "A": [
        "336726",
        "Venti-Best-Builds",
        "305872",
        "314345",
        "336727",
        "314174",
        "412428",
        "346199"
      ],
      "B": ["409556", "390096", "386486", "333496", "Dehya-Best-Builds"],
      "C": [
        "297533",
        "297517",
        "336865",
        "337141",
        "314177",
        "386384",
        "380569"
      ],
      "D": ["297532", "Lisa-Best-Builds", "305873", "297523"]
    }
  }
}
